{
    "os": "Linux-3.10.0-862.el7.x86_64-x86_64-with-glibc2.17",
    "python": "3.10.4",
    "heartbeatAt": "2022-12-21T16:23:26.121117",
    "startedAt": "2022-12-21T16:23:25.553742",
    "docker": null,
    "cuda": null,
    "args": [
        "--session_name",
        "",
        "--group_name",
        "NIID_10client",
        "--idx_path",
        "Dataset_scenarios/NIID_10clients_random.json",
        "--proportion",
        "0.5",
        "--algorithm",
        "fedalgo1",
        "--score",
        "all_gnorm_threshold",
        "--ratio",
        "0.8"
    ],
    "state": "running",
    "program": "/home/ace15032jo/Projects/SampleSelection_easyFL/main.py",
    "codePath": "main.py",
    "git": {
        "remote": "https://github.com/duclong1009/SampleSelection_easyFL.git",
        "commit": "12f2aca97fc04ef625a909491ac04c2031a79577"
    },
    "email": null,
    "root": "/home/ace15032jo/Projects/SampleSelection_easyFL",
    "host": "g0007.abci.local",
    "username": "ace15032jo",
    "executable": "/home/ace15032jo/venv/pytorch+horovod/bin/python",
    "cpu_count": 40,
    "cpu_count_logical": 80,
    "cpu_freq": {
        "current": 3096.6627624999996,
        "min": 1000.0,
        "max": 3700.0
    },
    "cpu_freq_per_core": [
        {
            "current": 3399.902,
            "min": 1000.0,
            "max": 3700.0
        },
        {
            "current": 3043.359,
            "min": 1000.0,
            "max": 3700.0
        },
        {
            "current": 2799.023,
            "min": 1000.0,
            "max": 3700.0
        },
        {
            "current": 3090.234,
            "min": 1000.0,
            "max": 3700.0
        },
        {
            "current": 3046.289,
            "min": 1000.0,
            "max": 3700.0
        },
        {
            "current": 3196.728,
            "min": 1000.0,
            "max": 3700.0
        },
        {
            "current": 3037.207,
            "min": 1000.0,
            "max": 3700.0
        },
        {
            "current": 3129.345,
            "min": 1000.0,
            "max": 3700.0
        },
        {
            "current": 3019.775,
            "min": 1000.0,
            "max": 3700.0
        },
        {
            "current": 2734.277,
            "min": 1000.0,
            "max": 3700.0
        },
        {
            "current": 3111.767,
            "min": 1000.0,
            "max": 3700.0
        },
        {
            "current": 3091.992,
            "min": 1000.0,
            "max": 3700.0
        },
        {
            "current": 3211.669,
            "min": 1000.0,
            "max": 3700.0
        },
        {
            "current": 3120.703,
            "min": 1000.0,
            "max": 3700.0
        },
        {
            "current": 3100.927,
            "min": 1000.0,
            "max": 3700.0
        },
        {
            "current": 3157.91,
            "min": 1000.0,
            "max": 3700.0
        },
        {
            "current": 3264.843,
            "min": 1000.0,
            "max": 3700.0
        },
        {
            "current": 3370.166,
            "min": 1000.0,
            "max": 3700.0
        },
        {
            "current": 3120.117,
            "min": 1000.0,
            "max": 3700.0
        },
        {
            "current": 3379.394,
            "min": 1000.0,
            "max": 3700.0
        },
        {
            "current": 3314.208,
            "min": 1000.0,
            "max": 3700.0
        },
        {
            "current": 3256.494,
            "min": 1000.0,
            "max": 3700.0
        },
        {
            "current": 3162.89,
            "min": 1000.0,
            "max": 3700.0
        },
        {
            "current": 3049.511,
            "min": 1000.0,
            "max": 3700.0
        },
        {
            "current": 2873.437,
            "min": 1000.0,
            "max": 3700.0
        },
        {
            "current": 2965.869,
            "min": 1000.0,
            "max": 3700.0
        },
        {
            "current": 3123.779,
            "min": 1000.0,
            "max": 3700.0
        },
        {
            "current": 3162.011,
            "min": 1000.0,
            "max": 3700.0
        },
        {
            "current": 3051.708,
            "min": 1000.0,
            "max": 3700.0
        },
        {
            "current": 3095.507,
            "min": 1000.0,
            "max": 3700.0
        },
        {
            "current": 2495.947,
            "min": 1000.0,
            "max": 3700.0
        },
        {
            "current": 3308.203,
            "min": 1000.0,
            "max": 3700.0
        },
        {
            "current": 2142.48,
            "min": 1000.0,
            "max": 3700.0
        },
        {
            "current": 3310.546,
            "min": 1000.0,
            "max": 3700.0
        },
        {
            "current": 3199.951,
            "min": 1000.0,
            "max": 3700.0
        },
        {
            "current": 3043.652,
            "min": 1000.0,
            "max": 3700.0
        },
        {
            "current": 2957.373,
            "min": 1000.0,
            "max": 3700.0
        },
        {
            "current": 3064.892,
            "min": 1000.0,
            "max": 3700.0
        },
        {
            "current": 3155.273,
            "min": 1000.0,
            "max": 3700.0
        },
        {
            "current": 2326.464,
            "min": 1000.0,
            "max": 3700.0
        },
        {
            "current": 3377.929,
            "min": 1000.0,
            "max": 3700.0
        },
        {
            "current": 2910.937,
            "min": 1000.0,
            "max": 3700.0
        },
        {
            "current": 3216.064,
            "min": 1000.0,
            "max": 3700.0
        },
        {
            "current": 3068.554,
            "min": 1000.0,
            "max": 3700.0
        },
        {
            "current": 3003.369,
            "min": 1000.0,
            "max": 3700.0
        },
        {
            "current": 3378.222,
            "min": 1000.0,
            "max": 3700.0
        },
        {
            "current": 2991.796,
            "min": 1000.0,
            "max": 3700.0
        },
        {
            "current": 3312.304,
            "min": 1000.0,
            "max": 3700.0
        },
        {
            "current": 3189.843,
            "min": 1000.0,
            "max": 3700.0
        },
        {
            "current": 2923.828,
            "min": 1000.0,
            "max": 3700.0
        },
        {
            "current": 3188.378,
            "min": 1000.0,
            "max": 3700.0
        },
        {
            "current": 3166.992,
            "min": 1000.0,
            "max": 3700.0
        },
        {
            "current": 2977.294,
            "min": 1000.0,
            "max": 3700.0
        },
        {
            "current": 3043.945,
            "min": 1000.0,
            "max": 3700.0
        },
        {
            "current": 3298.828,
            "min": 1000.0,
            "max": 3700.0
        },
        {
            "current": 3147.802,
            "min": 1000.0,
            "max": 3700.0
        },
        {
            "current": 3193.066,
            "min": 1000.0,
            "max": 3700.0
        },
        {
            "current": 3302.49,
            "min": 1000.0,
            "max": 3700.0
        },
        {
            "current": 3121.142,
            "min": 1000.0,
            "max": 3700.0
        },
        {
            "current": 3125.683,
            "min": 1000.0,
            "max": 3700.0
        },
        {
            "current": 3037.646,
            "min": 1000.0,
            "max": 3700.0
        },
        {
            "current": 3384.667,
            "min": 1000.0,
            "max": 3700.0
        },
        {
            "current": 3386.279,
            "min": 1000.0,
            "max": 3700.0
        },
        {
            "current": 3002.197,
            "min": 1000.0,
            "max": 3700.0
        },
        {
            "current": 2959.57,
            "min": 1000.0,
            "max": 3700.0
        },
        {
            "current": 3030.615,
            "min": 1000.0,
            "max": 3700.0
        },
        {
            "current": 2921.044,
            "min": 1000.0,
            "max": 3700.0
        },
        {
            "current": 3049.951,
            "min": 1000.0,
            "max": 3700.0
        },
        {
            "current": 2930.273,
            "min": 1000.0,
            "max": 3700.0
        },
        {
            "current": 2623.535,
            "min": 1000.0,
            "max": 3700.0
        },
        {
            "current": 3385.546,
            "min": 1000.0,
            "max": 3700.0
        },
        {
            "current": 3134.326,
            "min": 1000.0,
            "max": 3700.0
        },
        {
            "current": 3390.527,
            "min": 1000.0,
            "max": 3700.0
        },
        {
            "current": 3339.111,
            "min": 1000.0,
            "max": 3700.0
        },
        {
            "current": 3251.953,
            "min": 1000.0,
            "max": 3700.0
        },
        {
            "current": 3214.892,
            "min": 1000.0,
            "max": 3700.0
        },
        {
            "current": 2523.925,
            "min": 1000.0,
            "max": 3700.0
        },
        {
            "current": 3246.093,
            "min": 1000.0,
            "max": 3700.0
        },
        {
            "current": 3145.166,
            "min": 1000.0,
            "max": 3700.0
        },
        {
            "current": 2961.914,
            "min": 1000.0,
            "max": 3700.0
        }
    ],
    "disk": {
        "total": 15.992786407470703,
        "used": 11.753894805908203
    },
    "gpu": "Tesla V100-SXM2-16GB",
    "gpu_count": 1,
    "gpu_devices": [
        {
            "name": "Tesla V100-SXM2-16GB",
            "memory_total": 17179869184
        }
    ],
    "memory": {
        "total": 376.2051773071289
    }
}
